phonetic_bangla-1.0.0.dist-info/licenses/LICENSE
phoneticbn/__init__.py
phoneticbn/cli.py
phoneticbn/engine.py
phonetic_bangla-1.0.0.dist-info/METADATA
phonetic_bangla-1.0.0.dist-info/WHEEL
phonetic_bangla-1.0.0.dist-info/entry_points.txt
phonetic_bangla-1.0.0.dist-info/top_level.txt
phonetic_bangla-1.0.0.dist-info/RECORD
