Metadata-Version: 2.4
Name: phonetic-bangla
Version: 1.0.0
Summary: An intelligent, rule-based phonetic transliterator from English to Bengali.
Author-email: Mohaimenul Islam Shawon <mohaimenulislamshawon@gmail.com>
License: MIT License
Project-URL: Homepage, https://github.com/mohaimenulislamshawon/phonetic-bangla
Project-URL: Bug Tracker, https://github.com/mohaimenulislamshawon/phonetic-bangla/issues
Classifier: Programming Language :: Python :: 3
Classifier: License :: OSI Approved :: MIT License
Classifier: Operating System :: OS Independent
Classifier: Intended Audience :: Developers
Classifier: Topic :: Text Processing :: Linguistic
Requires-Python: >=3.7
License-File: LICENSE
Dynamic: license-file
